constellation_vpc/.gitignore
constellation_vpc/__init__.py
constellation_vpc/_vpc.py
constellation_vpc/errors.py
constellation_vpc/internet_gateway.py
constellation_vpc/nat_gateway.py
constellation_vpc/peering_connection.py
constellation_vpc/routing_table.py
constellation_vpc/subnet.py
constellation_vpc/vpc.py
constellation_vpc-0.5.0a4.dist-info/LICENSE
constellation_vpc-0.5.0a4.dist-info/METADATA
constellation_vpc-0.5.0a4.dist-info/WHEEL
constellation_vpc-0.5.0a4.dist-info/RECORD
