Metadata-Version: 2.1
Name: constellation_vpc
Version: 0.5.0a4
Summary: The VPC Module for constellation-aws
License: MIT
Author: Coulter Stutz
Author-email: coulterstutz@gmail.com
Requires-Python: >=3.9.19
Classifier: License :: OSI Approved :: MIT License
Classifier: Programming Language :: Python :: 3
Classifier: Programming Language :: Python :: 3.10
Classifier: Programming Language :: Python :: 3.11
Classifier: Programming Language :: Python :: 3.12
